{
    "FileVersion": "2.0.0",
    "EnableAddressable": true,
    "LocationToLower": false,
    "IncludeAssetGUID": false,
    "OutputNameStyle": 0,
    "BuildPipeline": "BuiltinBuildPipeline",
    "PackageName": "DefaultPackage",
    "PackageVersion": "Simulate",
    "AssetList": [
        {
            "Address": "Cube",
            "AssetPath": "Assets/Editor/MyGameAssets/GameRes/Effects/Cube.prefab",
            "AssetGUID": "",
            "AssetTags": [],
            "BundleID": 0
        },
        {
            "Address": "Sphere",
            "AssetPath": "Assets/Editor/MyGameAssets/GameRes/Role/Sphere.prefab",
            "AssetGUID": "",
            "AssetTags": [],
            "BundleID": 1
        },
        {
            "Address": "Sphere1",
            "AssetPath": "Assets/Editor/MyGameAssets/GameRes/Role/Sphere1.prefab",
            "AssetGUID": "",
            "AssetTags": [],
            "BundleID": 1
        },
        {
            "Address": "NewUnlitShader",
            "AssetPath": "Assets/Editor/MyGameAssets/GameRes/Shaders/NewUnlitShader.shader",
            "AssetGUID": "",
            "AssetTags": [],
            "BundleID": 2
        },
        {
            "Address": "EmptyScene",
            "AssetPath": "Assets/Editor/MyGameAssets/GameRes/Scenes/EmptyScene.unity",
            "AssetGUID": "",
            "AssetTags": [],
            "BundleID": 3
        },
        {
            "Address": "LoginScene",
            "AssetPath": "Assets/Editor/MyGameAssets/GameRes/Scenes/LoginScene.unity",
            "AssetGUID": "",
            "AssetTags": [],
            "BundleID": 3
        },
        {
            "Address": "UI_Plane",
            "AssetPath": "Assets/Editor/MyGameAssets/GameRes/UI/Plane.prefab",
            "AssetGUID": "",
            "AssetTags": [],
            "BundleID": 4
        },
        {
            "Address": "UI_UIRoot",
            "AssetPath": "Assets/Editor/MyGameAssets/GameRes/UI/UIRoot.prefab",
            "AssetGUID": "",
            "AssetTags": [],
            "BundleID": 4
        },
        {
            "Address": "Links",
            "AssetPath": "Assets/Editor/MyGameAssets/GameRes/ScriptObject/Links.asset",
            "AssetGUID": "",
            "AssetTags": [],
            "BundleID": 5
        },
        {
            "Address": "PoolConfig",
            "AssetPath": "Assets/Editor/MyGameAssets/GameRes/ScriptObject/PoolConfig.asset",
            "AssetGUID": "",
            "AssetTags": [],
            "BundleID": 5
        },
        {
            "Address": "New Material",
            "AssetPath": "Assets/Editor/MyGameAssets/GameRes/Bytes/New Material.mat",
            "AssetGUID": "",
            "AssetTags": [],
            "BundleID": 6
        },
        {
            "Address": "New Material1",
            "AssetPath": "Assets/Editor/MyGameAssets/GameRes/Materials/New Material1.mat",
            "AssetGUID": "",
            "AssetTags": [],
            "BundleID": 7
        },
        {
            "Address": "Lua_App.lua",
            "AssetPath": "Assets/Editor/MyGameAssets/ExtraRes/Lua/App.lua.txt",
            "AssetGUID": "",
            "AssetTags": [],
            "BundleID": 8
        },
        {
            "Address": "Lua_GamePrepareLoad.lua",
            "AssetPath": "Assets/Editor/MyGameAssets/ExtraRes/Lua/GamePrepareLoad.lua.txt",
            "AssetGUID": "",
            "AssetTags": [],
            "BundleID": 8
        },
        {
            "Address": "Lua_global.lua",
            "AssetPath": "Assets/Editor/MyGameAssets/ExtraRes/Lua/global.lua.txt",
            "AssetGUID": "",
            "AssetTags": [],
            "BundleID": 8
        },
        {
            "Address": "Lua_GlobalRequire.lua",
            "AssetPath": "Assets/Editor/MyGameAssets/ExtraRes/Lua/GlobalRequire.lua.txt",
            "AssetGUID": "",
            "AssetTags": [],
            "BundleID": 8
        },
        {
            "Address": "Lua_main.lua",
            "AssetPath": "Assets/Editor/MyGameAssets/ExtraRes/Lua/main.lua.txt",
            "AssetGUID": "",
            "AssetTags": [],
            "BundleID": 8
        },
        {
            "Address": "Lua_StartApp.lua",
            "AssetPath": "Assets/Editor/MyGameAssets/ExtraRes/Lua/StartApp.lua.txt",
            "AssetGUID": "",
            "AssetTags": [],
            "BundleID": 8
        },
        {
            "Address": "Lua_XLuaFacade.lua",
            "AssetPath": "Assets/Editor/MyGameAssets/ExtraRes/Lua/XLuaFacade.lua.txt",
            "AssetGUID": "",
            "AssetTags": [],
            "BundleID": 8
        },
        {
            "Address": "consts_AppEvent.lua",
            "AssetPath": "Assets/Editor/MyGameAssets/ExtraRes/Lua/consts/AppEvent.lua.txt",
            "AssetGUID": "",
            "AssetTags": [],
            "BundleID": 9
        },
        {
            "Address": "consts_CS_Define.lua",
            "AssetPath": "Assets/Editor/MyGameAssets/ExtraRes/Lua/consts/CS_Define.lua.txt",
            "AssetGUID": "",
            "AssetTags": [],
            "BundleID": 9
        },
        {
            "Address": "consts_Enum.lua",
            "AssetPath": "Assets/Editor/MyGameAssets/ExtraRes/Lua/consts/Enum.lua.txt",
            "AssetGUID": "",
            "AssetTags": [],
            "BundleID": 9
        },
        {
            "Address": "core_Lua_BaseClass.lua",
            "AssetPath": "Assets/Editor/MyGameAssets/ExtraRes/Lua/core/Lua_BaseClass.lua.txt",
            "AssetGUID": "",
            "AssetTags": [],
            "BundleID": 10
        },
        {
            "Address": "core_Lua_LazyClass.lua",
            "AssetPath": "Assets/Editor/MyGameAssets/ExtraRes/Lua/core/Lua_LazyClass.lua.txt",
            "AssetGUID": "",
            "AssetTags": [],
            "BundleID": 10
        },
        {
            "Address": "core_Lua_Messager.lua",
            "AssetPath": "Assets/Editor/MyGameAssets/ExtraRes/Lua/core/Lua_Messager.lua.txt",
            "AssetGUID": "",
            "AssetTags": [],
            "BundleID": 10
        },
        {
            "Address": "core_Lua_Object.lua",
            "AssetPath": "Assets/Editor/MyGameAssets/ExtraRes/Lua/core/Lua_Object.lua.txt",
            "AssetGUID": "",
            "AssetTags": [],
            "BundleID": 10
        },
        {
            "Address": "core_Lua_Singleton.lua",
            "AssetPath": "Assets/Editor/MyGameAssets/ExtraRes/Lua/core/Lua_Singleton.lua.txt",
            "AssetGUID": "",
            "AssetTags": [],
            "BundleID": 10
        },
        {
            "Address": "core_Lua_Updatable.lua",
            "AssetPath": "Assets/Editor/MyGameAssets/ExtraRes/Lua/core/Lua_Updatable.lua.txt",
            "AssetGUID": "",
            "AssetTags": [],
            "BundleID": 10
        },
        {
            "Address": "functions_init.lua",
            "AssetPath": "Assets/Editor/MyGameAssets/ExtraRes/Lua/functions/init.lua.txt",
            "AssetGUID": "",
            "AssetTags": [],
            "BundleID": 11
        },
        {
            "Address": "logic_SelectManager.lua",
            "AssetPath": "Assets/Editor/MyGameAssets/ExtraRes/Lua/logic/SelectManager.lua.txt",
            "AssetGUID": "",
            "AssetTags": [],
            "BundleID": 12
        },
        {
            "Address": "logic_SystemManager.lua",
            "AssetPath": "Assets/Editor/MyGameAssets/ExtraRes/Lua/logic/SystemManager.lua.txt",
            "AssetGUID": "",
            "AssetTags": [],
            "BundleID": 12
        },
        {
            "Address": "logic_TimeManager.lua",
            "AssetPath": "Assets/Editor/MyGameAssets/ExtraRes/Lua/logic/TimeManager.lua.txt",
            "AssetGUID": "",
            "AssetTags": [],
            "BundleID": 12
        },
        {
            "Address": "logic_UICache.lua",
            "AssetPath": "Assets/Editor/MyGameAssets/ExtraRes/Lua/logic/UICache.lua.txt",
            "AssetGUID": "",
            "AssetTags": [],
            "BundleID": 12
        },
        {
            "Address": "logic_UIManager.lua",
            "AssetPath": "Assets/Editor/MyGameAssets/ExtraRes/Lua/logic/UIManager.lua.txt",
            "AssetGUID": "",
            "AssetTags": [],
            "BundleID": 12
        },
        {
            "Address": "logic_UpdateManager.lua",
            "AssetPath": "Assets/Editor/MyGameAssets/ExtraRes/Lua/logic/UpdateManager.lua.txt",
            "AssetGUID": "",
            "AssetTags": [],
            "BundleID": 12
        },
        {
            "Address": "system_BaseSystem.lua",
            "AssetPath": "Assets/Editor/MyGameAssets/ExtraRes/Lua/system/BaseSystem.lua.txt",
            "AssetGUID": "",
            "AssetTags": [],
            "BundleID": 13
        },
        {
            "Address": "system_GameSettingSystem.lua",
            "AssetPath": "Assets/Editor/MyGameAssets/ExtraRes/Lua/system/GameSettingSystem.lua.txt",
            "AssetGUID": "",
            "AssetTags": [],
            "BundleID": 13
        },
        {
            "Address": "system_TestSystem.lua",
            "AssetPath": "Assets/Editor/MyGameAssets/ExtraRes/Lua/system/TestSystem.lua.txt",
            "AssetGUID": "",
            "AssetTags": [],
            "BundleID": 13
        },
        {
            "Address": "system_ValueObject.lua",
            "AssetPath": "Assets/Editor/MyGameAssets/ExtraRes/Lua/system/ValueObject.lua.txt",
            "AssetGUID": "",
            "AssetTags": [],
            "BundleID": 13
        },
        {
            "Address": "core_UIBaseCtrl.lua",
            "AssetPath": "Assets/Editor/MyGameAssets/ExtraRes/Lua/ui/core/UIBaseCtrl.lua.txt",
            "AssetGUID": "",
            "AssetTags": [],
            "BundleID": 14
        },
        {
            "Address": "utils_debug.lua",
            "AssetPath": "Assets/Editor/MyGameAssets/ExtraRes/Lua/utils/debug.lua.txt",
            "AssetGUID": "",
            "AssetTags": [],
            "BundleID": 15
        },
        {
            "Address": "utils_functions.lua",
            "AssetPath": "Assets/Editor/MyGameAssets/ExtraRes/Lua/utils/functions.lua.txt",
            "AssetGUID": "",
            "AssetTags": [],
            "BundleID": 15
        },
        {
            "Address": "utils_lc_event.lua",
            "AssetPath": "Assets/Editor/MyGameAssets/ExtraRes/Lua/utils/lc_event.lua.txt",
            "AssetGUID": "",
            "AssetTags": [],
            "BundleID": 15
        },
        {
            "Address": "utils_lc_list.lua",
            "AssetPath": "Assets/Editor/MyGameAssets/ExtraRes/Lua/utils/lc_list.lua.txt",
            "AssetGUID": "",
            "AssetTags": [],
            "BundleID": 15
        },
        {
            "Address": "utils_XLogger.lua",
            "AssetPath": "Assets/Editor/MyGameAssets/ExtraRes/Lua/utils/XLogger.lua.txt",
            "AssetGUID": "",
            "AssetTags": [],
            "BundleID": 15
        },
        {
            "Address": "Data_data1.lua",
            "AssetPath": "Assets/Editor/MyGameAssets/ExtraRes/Data/data1.lua.txt",
            "AssetGUID": "",
            "AssetTags": [],
            "BundleID": 16
        }
    ],
    "BundleList": [
        {
            "BundleName": "defaultpackage_assets_editor_mygameassets_gameres_effects.bundle",
            "UnityCRC": 0,
            "FileHash": "c8833fe830d74643553ae4e0123ddefb",
            "FileCRC": "00000000",
            "FileSize": 3207,
            "Encrypted": false,
            "Tags": [],
            "DependIDs": []
        },
        {
            "BundleName": "defaultpackage_assets_editor_mygameassets_gameres_role.bundle",
            "UnityCRC": 0,
            "FileHash": "133336903836182f1c4bb6ba30ba9802",
            "FileCRC": "00000000",
            "FileSize": 6397,
            "Encrypted": false,
            "Tags": [],
            "DependIDs": []
        },
        {
            "BundleName": "defaultpackage_unityshaders.bundle",
            "UnityCRC": 0,
            "FileHash": "fb82293786afa71a48aa1e33013a16be",
            "FileCRC": "00000000",
            "FileSize": 1409,
            "Encrypted": false,
            "Tags": [],
            "DependIDs": []
        },
        {
            "BundleName": "defaultpackage_assets_editor_mygameassets_gameres_scenes.bundle",
            "UnityCRC": 0,
            "FileHash": "c9ae78179655daf923437a46fbf57ed1",
            "FileCRC": "00000000",
            "FileSize": 23949,
            "Encrypted": false,
            "Tags": [],
            "DependIDs": []
        },
        {
            "BundleName": "defaultpackage_assets_editor_mygameassets_gameres_ui.bundle",
            "UnityCRC": 0,
            "FileHash": "b9fad68f0cc0a0bfb6c0daa24a9cde26",
            "FileCRC": "00000000",
            "FileSize": 13031,
            "Encrypted": false,
            "Tags": [],
            "DependIDs": []
        },
        {
            "BundleName": "defaultpackage_assets_editor_mygameassets_gameres_scriptobject.bundle",
            "UnityCRC": 0,
            "FileHash": "75fed8feb11b076b82c1a33de8aea6af",
            "FileCRC": "00000000",
            "FileSize": 1637,
            "Encrypted": false,
            "Tags": [],
            "DependIDs": []
        },
        {
            "BundleName": "defaultpackage_assets_editor_mygameassets_gameres_bytes.bundle",
            "UnityCRC": 0,
            "FileHash": "75842c50a6e1aa0765bbd85481419e91",
            "FileCRC": "00000000",
            "FileSize": 3826,
            "Encrypted": false,
            "Tags": [],
            "DependIDs": []
        },
        {
            "BundleName": "defaultpackage_assets_editor_mygameassets_gameres_materials.bundle",
            "UnityCRC": 0,
            "FileHash": "53f2b0dbbd8f792c72e994f798dc9f18",
            "FileCRC": "00000000",
            "FileSize": 3828,
            "Encrypted": false,
            "Tags": [],
            "DependIDs": []
        },
        {
            "BundleName": "defaultpackage_assets_editor_mygameassets_extrares_lua.bundle",
            "UnityCRC": 0,
            "FileHash": "25bc7103a47406d3507b7f298a0f7737",
            "FileCRC": "00000000",
            "FileSize": 8828,
            "Encrypted": false,
            "Tags": [],
            "DependIDs": []
        },
        {
            "BundleName": "defaultpackage_assets_editor_mygameassets_extrares_lua_consts.bundle",
            "UnityCRC": 0,
            "FileHash": "e3c5464f4a52f82b4d9dd23db7789ac8",
            "FileCRC": "00000000",
            "FileSize": 2462,
            "Encrypted": false,
            "Tags": [],
            "DependIDs": []
        },
        {
            "BundleName": "defaultpackage_assets_editor_mygameassets_extrares_lua_core.bundle",
            "UnityCRC": 0,
            "FileHash": "67f87057c6ce8b3a06f96a7c1d2eb679",
            "FileCRC": "00000000",
            "FileSize": 11499,
            "Encrypted": false,
            "Tags": [],
            "DependIDs": []
        },
        {
            "BundleName": "defaultpackage_assets_editor_mygameassets_extrares_lua_functions.bundle",
            "UnityCRC": 0,
            "FileHash": "b43757a87e2042f3b1b28cd6294f9ce8",
            "FileCRC": "00000000",
            "FileSize": 66,
            "Encrypted": false,
            "Tags": [],
            "DependIDs": []
        },
        {
            "BundleName": "defaultpackage_assets_editor_mygameassets_extrares_lua_logic.bundle",
            "UnityCRC": 0,
            "FileHash": "7a68deb76cd55399e78bdfe9c3b29b48",
            "FileCRC": "00000000",
            "FileSize": 7614,
            "Encrypted": false,
            "Tags": [],
            "DependIDs": []
        },
        {
            "BundleName": "defaultpackage_assets_editor_mygameassets_extrares_lua_system.bundle",
            "UnityCRC": 0,
            "FileHash": "147bea4dcd338c6fd9757d7c2f40af00",
            "FileCRC": "00000000",
            "FileSize": 4472,
            "Encrypted": false,
            "Tags": [],
            "DependIDs": []
        },
        {
            "BundleName": "defaultpackage_assets_editor_mygameassets_extrares_lua_ui_core.bundle",
            "UnityCRC": 0,
            "FileHash": "1cf7276e1e85d270fe601a43abc40930",
            "FileCRC": "00000000",
            "FileSize": 476,
            "Encrypted": false,
            "Tags": [],
            "DependIDs": []
        },
        {
            "BundleName": "defaultpackage_assets_editor_mygameassets_extrares_lua_utils.bundle",
            "UnityCRC": 0,
            "FileHash": "1e3e5323ba5d319be26c12167d7663dd",
            "FileCRC": "00000000",
            "FileSize": 50244,
            "Encrypted": false,
            "Tags": [],
            "DependIDs": []
        },
        {
            "BundleName": "defaultpackage_assets_editor_mygameassets_extrares_data.bundle",
            "UnityCRC": 0,
            "FileHash": "8a6ef262734a18f99abbcfd225ed6c27",
            "FileCRC": "00000000",
            "FileSize": 32,
            "Encrypted": false,
            "Tags": [],
            "DependIDs": []
        }
    ]
}